shub/__init__.py
shub/__main__.py
shub/bootstrap.py
shub/cancel.py
shub/compat.py
shub/config.py
shub/copy_eggs.py
shub/deploy.py
shub/deploy_egg.py
shub/deploy_reqs.py
shub/exceptions.py
shub/fetch_eggs.py
shub/items.py
shub/log.py
shub/login.py
shub/logout.py
shub/migrate_eggs.py
shub/requests.py
shub/schedule.py
shub/tool.py
shub/utils.py
shub/version.py
shub/image/__init__.py
shub/image/build.py
shub/image/check.py
shub/image/deploy.py
shub/image/init.py
shub/image/list.py
shub/image/push.py
shub/image/test.py
shub/image/upload.py
shub/image/utils.py
shub/image/run/__init__.py
shub/image/run/wrapper.py
shub-2.16.0.dist-info/licenses/LICENSE
shub-2.16.0.dist-info/METADATA
shub-2.16.0.dist-info/WHEEL
shub-2.16.0.dist-info/entry_points.txt
shub-2.16.0.dist-info/top_level.txt
shub-2.16.0.dist-info/RECORD
