Metadata-Version: 2.4
Name: shub
Version: 2.16.0
Summary: Scrapinghub Command Line Client
Home-page: https://shub.readthedocs.io/en/stable/
Author: Scrapinghub
Author-email: info@scrapinghub.com
Maintainer: Scrapinghub
Maintainer-email: info@scrapinghub.com
License: BSD
Classifier: Development Status :: 5 - Production/Stable
Classifier: Intended Audience :: Developers
Classifier: Natural Language :: English
Classifier: License :: OSI Approved :: BSD License
Classifier: Programming Language :: Python
Classifier: Programming Language :: Python :: 3.9
Classifier: Programming Language :: Python :: 3.10
Classifier: Programming Language :: Python :: 3.11
Classifier: Programming Language :: Python :: 3.12
Classifier: Programming Language :: Python :: 3.13
Classifier: Programming Language :: Python :: 3.14
Classifier: Operating System :: OS Independent
Classifier: Environment :: Console
Classifier: Topic :: Internet :: WWW/HTTP
Requires-Python: >=3.9
License-File: LICENSE
Requires-Dist: click
Requires-Dist: docker
Requires-Dist: importlib-metadata; python_version < "3.10"
Requires-Dist: packaging
Requires-Dist: pip
Requires-Dist: PyYAML
Requires-Dist: retrying
Requires-Dist: requests
Requires-Dist: scrapinghub>=2.3.1
Requires-Dist: setuptools
Requires-Dist: tqdm==4.55.1
Requires-Dist: toml
Dynamic: author
Dynamic: author-email
Dynamic: classifier
Dynamic: description
Dynamic: home-page
Dynamic: license
Dynamic: license-file
Dynamic: maintainer
Dynamic: maintainer-email
Dynamic: requires-dist
Dynamic: requires-python
Dynamic: summary
